{"fetched_at":"2026-07-17T17:37:50.156Z","source":"https://celestrak.org/NORAD/elements/gp.php?GROUP=iridium-NEXT&FORMAT=JSON","constellation":"iridium","records":[{"OBJECT_NAME":"IRIDIUM 106","OBJECT_ID":"2017-003A","EPOCH":"2026-07-17T02:18:10.303776","CLASSIFICATION_TYPE":"U","MEAN_MOTION":14.34217446,"ECCENTRICITY":0.00023105,"INCLINATION":86.3939,"RA_OF_ASC_NODE":76.05,"ARG_OF_PERICENTER":93.834,"MEAN_ANOMALY":266.312,"EPHEMERIS_TYPE":0,"NORAD_CAT_ID":41917,"ELEMENT_SET_NO":999,"REV_AT_EPOCH":49749,"BSTAR":0.000016276686,"MEAN_MOTION_DOT":6.5e-7,"MEAN_MOTION_DDOT":0},{"OBJECT_NAME":"IRIDIUM 103","OBJECT_ID":"2017-003B","EPOCH":"2026-07-16T17:37:34.188672","CLASSIFICATION_TYPE":"U","MEAN_MOTION":14.34217654,"ECCENTRICITY":0.00019023,"INCLINATION":86.3937,"RA_OF_ASC_NODE":76.1007,"ARG_OF_PERICENTER":83.7692,"MEAN_ANOMALY":276.3721,"EPHEMERIS_TYPE":0,"NORAD_CAT_ID":41918,"ELEMENT_SET_NO":999,"REV_AT_EPOCH":49746,"BSTAR":-0.000002013444,"MEAN_MOTION_DOT":1.4e-7,"MEAN_MOTION_DDOT":0},{"OBJECT_NAME":"IRIDIUM 109","OBJECT_ID":"2017-003C","EPOCH":"2026-07-16T17:46:42.116736","CLASSIFICATION_TYPE":"U","MEAN_MOTION":14.34222005,"ECCENTRICITY":0.00024728,"INCLINATION":86.3941,"RA_OF_ASC_NODE":76.1589,"ARG_OF_PERICENTER":97.3434,"MEAN_ANOMALY":262.8043,"EPHEMERIS_TYPE":0,"NORAD_CAT_ID":41919,"ELEMENT_SET_NO":999,"REV_AT_EPOCH":49743,"BSTAR":0.000066934991,"MEAN_MOTION_DOT":0.00000207,"MEAN_MOTION_DDOT":0},{"OBJECT_NAME":"IRIDIUM 102","OBJECT_ID":"2017-003D","EPOCH":"2026-07-17T01:23:22.140096","CLASSIFICATION_TYPE":"U","MEAN_MOTION":14.34218901,"ECCENTRICITY":0.00022314,"INCLINATION":86.3938,"RA_OF_ASC_NODE":75.9485,"ARG_OF_PERICENTER":84.804,"MEAN_ANOMALY":275.341,"EPHEMERIS_TYPE":0,"NORAD_CAT_ID":41920,"ELEMENT_SET_NO":999,"REV_AT_EPOCH":49756,"BSTAR":0.000040076023,"MEAN_MOTION_DOT":0.00000132,"MEAN_MOTION_DDOT":0},{"OBJECT_NAME":"IRIDIUM 105","OBJECT_ID":"2017-003E","EPOCH":"2026-07-17T00:23:44.966688","CLASSIFICATION_TYPE":"U","MEAN_MOTION":14.34217183,"ECCENTRICITY":0.0002116,"INCLINATION":86.3942,"RA_OF_ASC_NODE":44.3933,"ARG_OF_PERICENTER":81.3221,"MEAN_ANOMALY":278.8214,"EPHEMERIS_TYPE":0,"NORAD_CAT_ID":41921,"ELEMENT_SET_NO":999,"REV_AT_EPOCH":49941,"BSTAR":0.000019834964,"MEAN_MOTION_DOT":7.5e-7,"MEAN_MOTION_DDOT":0},{"OBJECT_NAME":"IRIDIUM 104","OBJECT_ID":"2017-003F","EPOCH":"2026-07-17T01:41:38.162112","CLASSIFICATION_TYPE":"U","MEAN_MOTION":14.34218056,"ECCENTRICITY":0.00020107,"INCLINATION":86.394,"RA_OF_ASC_NODE":75.9859,"ARG_OF_PERICENTER":80.4947,"MEAN_ANOMALY":279.6476,"EPHEMERIS_TYPE":0,"NORAD_CAT_ID":41922,"ELEMENT_SET_NO":999,"REV_AT_EPOCH":49755,"BSTAR":0.000022664249,"MEAN_MOTION_DOT":8.3e-7,"MEAN_MOTION_DDOT":0},{"OBJECT_NAME":"IRIDIUM 114","OBJECT_ID":"2017-003G","EPOCH":"2026-07-17T03:31:14.296800","CLASSIFICATION_TYPE":"U","MEAN_MOTION":14.3421734,"ECCENTRICITY":0.00019258,"INCLINATION":86.3939,"RA_OF_ASC_NODE":75.937,"ARG_OF_PERICENTER":84.9277,"MEAN_ANOMALY":275.2139,"EPHEMERIS_TYPE":0,"NORAD_CAT_ID":41923,"ELEMENT_SET_NO":999,"REV_AT_EPOCH":49754,"BSTAR":0.000004538144,"MEAN_MOTION_DOT":3.2e-7,"MEAN_MOTION_DDOT":0},{"OBJECT_NAME":"IRIDIUM 108","OBJECT_ID":"2017-003H","EPOCH":"2026-07-17T00:51:02.474784","CLASSIFICATION_TYPE":"U","MEAN_MOTION":14.34217782,"ECCENTRICITY":0.0002223,"INCLINATION":86.3936,"RA_OF_ASC_NODE":44.2735,"ARG_OF_PERICENTER":85.3068,"MEAN_ANOMALY":274.8382,"EPHEMERIS_TYPE":0,"NORAD_CAT_ID":41924,"ELEMENT_SET_NO":999,"REV_AT_EPOCH":49938,"BSTAR":0.000013262716,"MEAN_MOTION_DOT":5.7e-7,"MEAN_MOTION_DDOT":0},{"OBJECT_NAME":"IRIDIUM 112","OBJECT_ID":"2017-003J","EPOCH":"2026-07-17T01:32:30.258240","CLASSIFICATION_TYPE":"U","MEAN_MOTION":14.34216926,"ECCENTRICITY":0.00021835,"INCLINATION":86.3935,"RA_OF_ASC_NODE":75.8125,"ARG_OF_PERICENTER":84.5763,"MEAN_ANOMALY":275.5682,"EPHEMERIS_TYPE":0,"NORAD_CAT_ID":41925,"ELEMENT_SET_NO":999,"REV_AT_EPOCH":49755,"BSTAR":0.000012794577,"MEAN_MOTION_DOT":5.6e-7,"MEAN_MOTION_DDOT":0},{"OBJECT_NAME":"IRIDIUM 111","OBJECT_ID":"2017-003K","EPOCH":"2026-07-17T04:35:10.208832","CLASSIFICATION_TYPE":"U","MEAN_MOTION":14.342181,"ECCENTRICITY":0.00021646,"INCLINATION":86.3938,"RA_OF_ASC_NODE":75.8308,"ARG_OF_PERICENTER":86.2701,"MEAN_ANOMALY":273.8742,"EPHEMERIS_TYPE":0,"NORAD_CAT_ID":41926,"ELEMENT_SET_NO":999,"REV_AT_EPOCH":49755,"BSTAR":0.000019346379,"MEAN_MOTION_DOT":7.4e-7,"MEAN_MOTION_DDOT":0},{"OBJECT_NAME":"IRIDIUM 113","OBJECT_ID":"2017-039A","EPOCH":"2026-07-17T05:46:47.161632","CLASSIFICATION_TYPE":"U","MEAN_MOTION":14.3421762,"ECCENTRICITY":0.00021325,"INCLINATION":86.3992,"RA_OF_ASC_NODE":309.6181,"ARG_OF_PERICENTER":92.6766,"MEAN_ANOMALY":267.4674,"EPHEMERIS_TYPE":0,"NORAD_CAT_ID":42803,"ELEMENT_SET_NO":999,"REV_AT_EPOCH":47549,"BSTAR":0.00001719793,"MEAN_MOTION_DOT":6.8e-7,"MEAN_MOTION_DDOT":0},{"OBJECT_NAME":"IRIDIUM 123","OBJECT_ID":"2017-039B","EPOCH":"2026-07-16T22:24:10.872288","CLASSIFICATION_TYPE":"U","MEAN_MOTION":14.34217616,"ECCENTRICITY":0.00021619,"INCLINATION":86.3995,"RA_OF_ASC_NODE":341.2026,"ARG_OF_PERICENTER":96.1194,"MEAN_ANOMALY":264.0248,"EPHEMERIS_TYPE":0,"NORAD_CAT_ID":42804,"ELEMENT_SET_NO":999,"REV_AT_EPOCH":47421,"BSTAR":0.000011209555,"MEAN_MOTION_DOT":5.1e-7,"MEAN_MOTION_DDOT":0},{"OBJECT_NAME":"IRIDIUM 120","OBJECT_ID":"2017-039C","EPOCH":"2026-07-16T19:34:51.228480","CLASSIFICATION_TYPE":"U","MEAN_MOTION":14.34218164,"ECCENTRICITY":0.00023678,"INCLINATION":86.398,"RA_OF_ASC_NODE":309.5742,"ARG_OF_PERICENTER":97.6896,"MEAN_ANOMALY":262.4568,"EPHEMERIS_TYPE":0,"NORAD_CAT_ID":42805,"ELEMENT_SET_NO":999,"REV_AT_EPOCH":47542,"BSTAR":0.000017065725,"MEAN_MOTION_DOT":6.8e-7,"MEAN_MOTION_DDOT":0},{"OBJECT_NAME":"IRIDIUM 115","OBJECT_ID":"2017-039D","EPOCH":"2026-07-16T20:40:35.174208","CLASSIFICATION_TYPE":"U","MEAN_MOTION":14.43278142,"ECCENTRICITY":0.00022679,"INCLINATION":86.4518,"RA_OF_ASC_NODE":309.6881,"ARG_OF_PERICENTER":99.331,"MEAN_ANOMALY":260.8147,"EPHEMERIS_TYPE":0,"NORAD_CAT_ID":42806,"ELEMENT_SET_NO":999,"REV_AT_EPOCH":47854,"BSTAR":0.000047330734,"MEAN_MOTION_DOT":0.00000179,"MEAN_MOTION_DDOT":0},{"OBJECT_NAME":"IRIDIUM 118","OBJECT_ID":"2017-039E","EPOCH":"2026-07-16T21:29:23.012736","CLASSIFICATION_TYPE":"U","MEAN_MOTION":14.34217491,"ECCENTRICITY":0.00021906,"INCLINATION":86.3994,"RA_OF_ASC_NODE":341.2162,"ARG_OF_PERICENTER":91.3252,"MEAN_ANOMALY":268.8194,"EPHEMERIS_TYPE":0,"NORAD_CAT_ID":42807,"ELEMENT_SET_NO":999,"REV_AT_EPOCH":47420,"BSTAR":4.6749e-7,"MEAN_MOTION_DOT":2.1e-7,"MEAN_MOTION_DDOT":0},{"OBJECT_NAME":"IRIDIUM 117","OBJECT_ID":"2017-039F","EPOCH":"2026-07-17T07:59:34.879776","CLASSIFICATION_TYPE":"U","MEAN_MOTION":14.34217669,"ECCENTRICITY":0.00021724,"INCLINATION":86.3993,"RA_OF_ASC_NODE":340.9906,"ARG_OF_PERICENTER":94.3564,"MEAN_ANOMALY":265.788,"EPHEMERIS_TYPE":0,"NORAD_CAT_ID":42808,"ELEMENT_SET_NO":999,"REV_AT_EPOCH":47429,"BSTAR":0.000019132046,"MEAN_MOTION_DOT":7.3e-7,"MEAN_MOTION_DDOT":0},{"OBJECT_NAME":"IRIDIUM 126","OBJECT_ID":"2017-039G","EPOCH":"2026-07-16T22:33:18.957600","CLASSIFICATION_TYPE":"U","MEAN_MOTION":14.34217499,"ECCENTRICITY":0.00020659,"INCLINATION":86.3993,"RA_OF_ASC_NODE":341.2067,"ARG_OF_PERICENTER":91.5832,"MEAN_ANOMALY":268.5601,"EPHEMERIS_TYPE":0,"NORAD_CAT_ID":42809,"ELEMENT_SET_NO":999,"REV_AT_EPOCH":47421,"BSTAR":-0.000004965723,"MEAN_MOTION_DOT":6e-8,"MEAN_MOTION_DDOT":0},{"OBJECT_NAME":"IRIDIUM 124","OBJECT_ID":"2017-039H","EPOCH":"2026-07-16T17:25:23.146176","CLASSIFICATION_TYPE":"U","MEAN_MOTION":14.43274638,"ECCENTRICITY":0.00022183,"INCLINATION":86.4483,"RA_OF_ASC_NODE":278.0086,"ARG_OF_PERICENTER":96.6229,"MEAN_ANOMALY":263.5225,"EPHEMERIS_TYPE":0,"NORAD_CAT_ID":42810,"ELEMENT_SET_NO":999,"REV_AT_EPOCH":47937,"BSTAR":0.000048434624,"MEAN_MOTION_DOT":0.00000183,"MEAN_MOTION_DDOT":0},{"OBJECT_NAME":"IRIDIUM 128","OBJECT_ID":"2017-039J","EPOCH":"2026-07-17T05:01:51.002976","CLASSIFICATION_TYPE":"U","MEAN_MOTION":14.34217128,"ECCENTRICITY":0.00022703,"INCLINATION":86.3967,"RA_OF_ASC_NODE":12.5944,"ARG_OF_PERICENTER":93.7418,"MEAN_ANOMALY":266.4037,"EPHEMERIS_TYPE":0,"NORAD_CAT_ID":42811,"ELEMENT_SET_NO":999,"REV_AT_EPOCH":47428,"BSTAR":0.000012183677,"MEAN_MOTION_DOT":5.4e-7,"MEAN_MOTION_DDOT":0},{"OBJECT_NAME":"IRIDIUM 121","OBJECT_ID":"2017-039K","EPOCH":"2026-07-17T04:02:06.959040","CLASSIFICATION_TYPE":"U","MEAN_MOTION":14.34217696,"ECCENTRICITY":0.00022362,"INCLINATION":86.3994,"RA_OF_ASC_NODE":341.1394,"ARG_OF_PERICENTER":92.4243,"MEAN_ANOMALY":267.7209,"EPHEMERIS_TYPE":0,"NORAD_CAT_ID":42812,"ELEMENT_SET_NO":999,"REV_AT_EPOCH":47412,"BSTAR":0.000005384231,"MEAN_MOTION_DOT":3.5e-7,"MEAN_MOTION_DDOT":0},{"OBJECT_NAME":"IRIDIUM 133","OBJECT_ID":"2017-061A","EPOCH":"2026-07-17T05:47:30.803136","CLASSIFICATION_TYPE":"U","MEAN_MOTION":14.34217448,"ECCENTRICITY":0.00022188,"INCLINATION":86.397,"RA_OF_ASC_NODE":12.6997,"ARG_OF_PERICENTER":91.329,"MEAN_ANOMALY":268.8161,"EPHEMERIS_TYPE":0,"NORAD_CAT_ID":42955,"ELEMENT_SET_NO":999,"REV_AT_EPOCH":45908,"BSTAR":0.000012202825,"MEAN_MOTION_DOT":5.4e-7,"MEAN_MOTION_DDOT":0},{"OBJECT_NAME":"IRIDIUM 100","OBJECT_ID":"2017-061B","EPOCH":"2026-07-16T12:53:42.916992","CLASSIFICATION_TYPE":"U","MEAN_MOTION":14.34217403,"ECCENTRICITY":0.00022184,"INCLINATION":86.3965,"RA_OF_ASC_NODE":12.9119,"ARG_OF_PERICENTER":90.1682,"MEAN_ANOMALY":269.9768,"EPHEMERIS_TYPE":0,"NORAD_CAT_ID":42956,"ELEMENT_SET_NO":999,"REV_AT_EPOCH":45898,"BSTAR":0.000008562295,"MEAN_MOTION_DOT":4.4e-7,"MEAN_MOTION_DDOT":0},{"OBJECT_NAME":"IRIDIUM 122","OBJECT_ID":"2017-061C","EPOCH":"2026-07-17T04:52:42.534912","CLASSIFICATION_TYPE":"U","MEAN_MOTION":14.34217454,"ECCENTRICITY":0.00021063,"INCLINATION":86.3967,"RA_OF_ASC_NODE":12.6338,"ARG_OF_PERICENTER":91.2466,"MEAN_ANOMALY":268.8971,"EPHEMERIS_TYPE":0,"NORAD_CAT_ID":42957,"ELEMENT_SET_NO":999,"REV_AT_EPOCH":45908,"BSTAR":0.000012583863,"MEAN_MOTION_DOT":5.5e-7,"MEAN_MOTION_DDOT":0},{"OBJECT_NAME":"IRIDIUM 129","OBJECT_ID":"2017-061D","EPOCH":"2026-07-17T00:27:50.647680","CLASSIFICATION_TYPE":"U","MEAN_MOTION":14.34217291,"ECCENTRICITY":0.00021044,"INCLINATION":86.3968,"RA_OF_ASC_NODE":12.778,"ARG_OF_PERICENTER":84.002,"MEAN_ANOMALY":276.1416,"EPHEMERIS_TYPE":0,"NORAD_CAT_ID":42958,"ELEMENT_SET_NO":999,"REV_AT_EPOCH":45907,"BSTAR":0.000010018842,"MEAN_MOTION_DOT":4.8e-7,"MEAN_MOTION_DDOT":0},{"OBJECT_NAME":"IRIDIUM 119","OBJECT_ID":"2017-061E","EPOCH":"2026-07-16T23:42:10.943424","CLASSIFICATION_TYPE":"U","MEAN_MOTION":14.34217069,"ECCENTRICITY":0.00021018,"INCLINATION":86.3969,"RA_OF_ASC_NODE":12.7871,"ARG_OF_PERICENTER":91.06,"MEAN_ANOMALY":269.0836,"EPHEMERIS_TYPE":0,"NORAD_CAT_ID":42959,"ELEMENT_SET_NO":999,"REV_AT_EPOCH":45908,"BSTAR":0.000013400498,"MEAN_MOTION_DOT":5.7e-7,"MEAN_MOTION_DDOT":0},{"OBJECT_NAME":"IRIDIUM 107","OBJECT_ID":"2017-061F","EPOCH":"2026-07-17T05:10:58.681344","CLASSIFICATION_TYPE":"U","MEAN_MOTION":14.34217572,"ECCENTRICITY":0.00021282,"INCLINATION":86.397,"RA_OF_ASC_NODE":12.7131,"ARG_OF_PERICENTER":97.2746,"MEAN_ANOMALY":262.8692,"EPHEMERIS_TYPE":0,"NORAD_CAT_ID":42960,"ELEMENT_SET_NO":999,"REV_AT_EPOCH":45912,"BSTAR":0.000014666605,"MEAN_MOTION_DOT":6.1e-7,"MEAN_MOTION_DDOT":0},{"OBJECT_NAME":"IRIDIUM 132","OBJECT_ID":"2017-061G","EPOCH":"2026-07-17T05:20:06.886752","CLASSIFICATION_TYPE":"U","MEAN_MOTION":14.34216943,"ECCENTRICITY":0.00021853,"INCLINATION":86.3967,"RA_OF_ASC_NODE":12.6897,"ARG_OF_PERICENTER":91.2775,"MEAN_ANOMALY":268.8671,"EPHEMERIS_TYPE":0,"NORAD_CAT_ID":42961,"ELEMENT_SET_NO":999,"REV_AT_EPOCH":45912,"BSTAR":0.000011541366,"MEAN_MOTION_DOT":5.2e-7,"MEAN_MOTION_DDOT":0},{"OBJECT_NAME":"IRIDIUM 136","OBJECT_ID":"2017-061H","EPOCH":"2026-07-16T23:23:54.900672","CLASSIFICATION_TYPE":"U","MEAN_MOTION":14.34217501,"ECCENTRICITY":0.00022406,"INCLINATION":86.3969,"RA_OF_ASC_NODE":12.8,"ARG_OF_PERICENTER":90.2029,"MEAN_ANOMALY":269.9423,"EPHEMERIS_TYPE":0,"NORAD_CAT_ID":42962,"ELEMENT_SET_NO":999,"REV_AT_EPOCH":45910,"BSTAR":0.000011830397,"MEAN_MOTION_DOT":5.3e-7,"MEAN_MOTION_DDOT":0},{"OBJECT_NAME":"IRIDIUM 139","OBJECT_ID":"2017-061J","EPOCH":"2026-07-16T23:33:02.976480","CLASSIFICATION_TYPE":"U","MEAN_MOTION":14.34217437,"ECCENTRICITY":0.00022557,"INCLINATION":86.3971,"RA_OF_ASC_NODE":12.8597,"ARG_OF_PERICENTER":92.6726,"MEAN_ANOMALY":267.4728,"EPHEMERIS_TYPE":0,"NORAD_CAT_ID":42963,"ELEMENT_SET_NO":999,"REV_AT_EPOCH":45911,"BSTAR":0.000011749007,"MEAN_MOTION_DOT":5.3e-7,"MEAN_MOTION_DDOT":0},{"OBJECT_NAME":"IRIDIUM 125","OBJECT_ID":"2017-061K","EPOCH":"2026-07-16T23:14:46.898304","CLASSIFICATION_TYPE":"U","MEAN_MOTION":14.34217701,"ECCENTRICITY":0.00016663,"INCLINATION":86.3971,"RA_OF_ASC_NODE":12.9266,"ARG_OF_PERICENTER":94.1672,"MEAN_ANOMALY":265.9714,"EPHEMERIS_TYPE":0,"NORAD_CAT_ID":42964,"ELEMENT_SET_NO":999,"REV_AT_EPOCH":45912,"BSTAR":0.000009679327,"MEAN_MOTION_DOT":4.7e-7,"MEAN_MOTION_DDOT":0},{"OBJECT_NAME":"IRIDIUM 135","OBJECT_ID":"2017-083A","EPOCH":"2026-07-17T06:59:51.178848","CLASSIFICATION_TYPE":"U","MEAN_MOTION":14.34218067,"ECCENTRICITY":0.00022151,"INCLINATION":86.3985,"RA_OF_ASC_NODE":309.4317,"ARG_OF_PERICENTER":94.4062,"MEAN_ANOMALY":265.7387,"EPHEMERIS_TYPE":0,"NORAD_CAT_ID":43070,"ELEMENT_SET_NO":999,"REV_AT_EPOCH":44846,"BSTAR":0.000013676646,"MEAN_MOTION_DOT":5.8e-7,"MEAN_MOTION_DDOT":0},{"OBJECT_NAME":"IRIDIUM 138","OBJECT_ID":"2017-083B","EPOCH":"2026-07-17T05:55:54.934176","CLASSIFICATION_TYPE":"U","MEAN_MOTION":14.3421912,"ECCENTRICITY":0.00020609,"INCLINATION":86.3999,"RA_OF_ASC_NODE":309.1504,"ARG_OF_PERICENTER":92.8202,"MEAN_ANOMALY":267.323,"EPHEMERIS_TYPE":0,"NORAD_CAT_ID":43071,"ELEMENT_SET_NO":999,"REV_AT_EPOCH":44844,"BSTAR":0.000043166201,"MEAN_MOTION_DOT":0.00000141,"MEAN_MOTION_DDOT":0},{"OBJECT_NAME":"IRIDIUM 116","OBJECT_ID":"2017-083C","EPOCH":"2026-07-17T06:50:43.065024","CLASSIFICATION_TYPE":"U","MEAN_MOTION":14.34218141,"ECCENTRICITY":0.0002498,"INCLINATION":86.3985,"RA_OF_ASC_NODE":309.4198,"ARG_OF_PERICENTER":97.558,"MEAN_ANOMALY":262.5899,"EPHEMERIS_TYPE":0,"NORAD_CAT_ID":43072,"ELEMENT_SET_NO":999,"REV_AT_EPOCH":44848,"BSTAR":0.000037483073,"MEAN_MOTION_DOT":0.00000125,"MEAN_MOTION_DDOT":0},{"OBJECT_NAME":"IRIDIUM 130","OBJECT_ID":"2017-083D","EPOCH":"2026-07-17T06:05:03.358176","CLASSIFICATION_TYPE":"U","MEAN_MOTION":14.34218427,"ECCENTRICITY":0.00023062,"INCLINATION":86.3994,"RA_OF_ASC_NODE":309.7114,"ARG_OF_PERICENTER":100.5978,"MEAN_ANOMALY":259.5478,"EPHEMERIS_TYPE":0,"NORAD_CAT_ID":43073,"ELEMENT_SET_NO":999,"REV_AT_EPOCH":44842,"BSTAR":0.000042935166,"MEAN_MOTION_DOT":0.0000014,"MEAN_MOTION_DDOT":0},{"OBJECT_NAME":"IRIDIUM 151","OBJECT_ID":"2017-083E","EPOCH":"2026-07-16T19:25:43.204512","CLASSIFICATION_TYPE":"U","MEAN_MOTION":14.34218196,"ECCENTRICITY":0.00022594,"INCLINATION":86.3987,"RA_OF_ASC_NODE":309.6771,"ARG_OF_PERICENTER":95.0471,"MEAN_ANOMALY":265.0983,"EPHEMERIS_TYPE":0,"NORAD_CAT_ID":43074,"ELEMENT_SET_NO":999,"REV_AT_EPOCH":44838,"BSTAR":0.000030524279,"MEAN_MOTION_DOT":0.00000105,"MEAN_MOTION_DDOT":0},{"OBJECT_NAME":"IRIDIUM 134","OBJECT_ID":"2017-083F","EPOCH":"2026-07-17T06:23:19.209120","CLASSIFICATION_TYPE":"U","MEAN_MOTION":14.34217795,"ECCENTRICITY":0.00022452,"INCLINATION":86.399,"RA_OF_ASC_NODE":309.4946,"ARG_OF_PERICENTER":95.7706,"MEAN_ANOMALY":264.3746,"EPHEMERIS_TYPE":0,"NORAD_CAT_ID":43075,"ELEMENT_SET_NO":999,"REV_AT_EPOCH":44841,"BSTAR":0.000007011484,"MEAN_MOTION_DOT":3.9e-7,"MEAN_MOTION_DDOT":0},{"OBJECT_NAME":"IRIDIUM 137","OBJECT_ID":"2017-083G","EPOCH":"2026-07-17T06:41:35.279520","CLASSIFICATION_TYPE":"U","MEAN_MOTION":14.34217951,"ECCENTRICITY":0.0002688,"INCLINATION":86.3991,"RA_OF_ASC_NODE":309.5829,"ARG_OF_PERICENTER":92.8597,"MEAN_ANOMALY":267.2907,"EPHEMERIS_TYPE":0,"NORAD_CAT_ID":43076,"ELEMENT_SET_NO":999,"REV_AT_EPOCH":44848,"BSTAR":0.000010448388,"MEAN_MOTION_DOT":4.9e-7,"MEAN_MOTION_DDOT":0},{"OBJECT_NAME":"IRIDIUM 141","OBJECT_ID":"2017-083H","EPOCH":"2026-07-17T06:32:27.147552","CLASSIFICATION_TYPE":"U","MEAN_MOTION":14.34217902,"ECCENTRICITY":0.00021784,"INCLINATION":86.3985,"RA_OF_ASC_NODE":309.4144,"ARG_OF_PERICENTER":93.7356,"MEAN_ANOMALY":266.4089,"EPHEMERIS_TYPE":0,"NORAD_CAT_ID":43077,"ELEMENT_SET_NO":999,"REV_AT_EPOCH":44848,"BSTAR":0.000021552812,"MEAN_MOTION_DOT":8e-7,"MEAN_MOTION_DDOT":0},{"OBJECT_NAME":"IRIDIUM 153","OBJECT_ID":"2017-083J","EPOCH":"2026-07-17T05:23:35.398464","CLASSIFICATION_TYPE":"U","MEAN_MOTION":14.34217841,"ECCENTRICITY":0.00021323,"INCLINATION":86.3959,"RA_OF_ASC_NODE":277.9134,"ARG_OF_PERICENTER":95.2478,"MEAN_ANOMALY":264.8961,"EPHEMERIS_TYPE":0,"NORAD_CAT_ID":43078,"ELEMENT_SET_NO":999,"REV_AT_EPOCH":44958,"BSTAR":0.000011129285,"MEAN_MOTION_DOT":5.1e-7,"MEAN_MOTION_DDOT":0},{"OBJECT_NAME":"IRIDIUM 131","OBJECT_ID":"2017-083K","EPOCH":"2026-07-17T07:54:39.167136","CLASSIFICATION_TYPE":"U","MEAN_MOTION":14.34218109,"ECCENTRICITY":0.00022266,"INCLINATION":86.399,"RA_OF_ASC_NODE":309.5786,"ARG_OF_PERICENTER":94.5395,"MEAN_ANOMALY":265.6055,"EPHEMERIS_TYPE":0,"NORAD_CAT_ID":43079,"ELEMENT_SET_NO":999,"REV_AT_EPOCH":44842,"BSTAR":0.000014271476,"MEAN_MOTION_DOT":6e-7,"MEAN_MOTION_DDOT":0},{"OBJECT_NAME":"IRIDIUM 144","OBJECT_ID":"2018-030A","EPOCH":"2026-07-17T03:52:15.348864","CLASSIFICATION_TYPE":"U","MEAN_MOTION":14.3421836,"ECCENTRICITY":0.00024002,"INCLINATION":86.3955,"RA_OF_ASC_NODE":277.8683,"ARG_OF_PERICENTER":96.645,"MEAN_ANOMALY":263.5019,"EPHEMERIS_TYPE":0,"NORAD_CAT_ID":43249,"ELEMENT_SET_NO":999,"REV_AT_EPOCH":43443,"BSTAR":0.000024428658,"MEAN_MOTION_DOT":8.8e-7,"MEAN_MOTION_DDOT":0},{"OBJECT_NAME":"IRIDIUM 149","OBJECT_ID":"2018-030B","EPOCH":"2026-07-17T05:41:51.420480","CLASSIFICATION_TYPE":"U","MEAN_MOTION":14.3421802,"ECCENTRICITY":0.00022535,"INCLINATION":86.3955,"RA_OF_ASC_NODE":277.8031,"ARG_OF_PERICENTER":93.4659,"MEAN_ANOMALY":266.6795,"EPHEMERIS_TYPE":0,"NORAD_CAT_ID":43250,"ELEMENT_SET_NO":999,"REV_AT_EPOCH":43446,"BSTAR":0.000017309112,"MEAN_MOTION_DOT":6.8e-7,"MEAN_MOTION_DDOT":0},{"OBJECT_NAME":"IRIDIUM 157","OBJECT_ID":"2018-030C","EPOCH":"2026-07-17T04:28:47.570016","CLASSIFICATION_TYPE":"U","MEAN_MOTION":14.34218501,"ECCENTRICITY":0.00022694,"INCLINATION":86.3958,"RA_OF_ASC_NODE":277.8784,"ARG_OF_PERICENTER":94.1706,"MEAN_ANOMALY":265.975,"EPHEMERIS_TYPE":0,"NORAD_CAT_ID":43251,"ELEMENT_SET_NO":999,"REV_AT_EPOCH":43443,"BSTAR":0.000042136092,"MEAN_MOTION_DOT":0.00000138,"MEAN_MOTION_DDOT":0},{"OBJECT_NAME":"IRIDIUM 140","OBJECT_ID":"2018-030D","EPOCH":"2026-07-17T04:56:11.629824","CLASSIFICATION_TYPE":"U","MEAN_MOTION":14.34218117,"ECCENTRICITY":0.00022516,"INCLINATION":86.3957,"RA_OF_ASC_NODE":277.8828,"ARG_OF_PERICENTER":95.7254,"MEAN_ANOMALY":264.4199,"EPHEMERIS_TYPE":0,"NORAD_CAT_ID":43252,"ELEMENT_SET_NO":999,"REV_AT_EPOCH":43449,"BSTAR":0.000043063829,"MEAN_MOTION_DOT":0.0000014,"MEAN_MOTION_DDOT":0},{"OBJECT_NAME":"IRIDIUM 145","OBJECT_ID":"2018-030E","EPOCH":"2026-07-17T04:37:55.427232","CLASSIFICATION_TYPE":"U","MEAN_MOTION":14.34217625,"ECCENTRICITY":0.00025708,"INCLINATION":86.3956,"RA_OF_ASC_NODE":277.8601,"ARG_OF_PERICENTER":99.6724,"MEAN_ANOMALY":260.4762,"EPHEMERIS_TYPE":0,"NORAD_CAT_ID":43253,"ELEMENT_SET_NO":999,"REV_AT_EPOCH":43442,"BSTAR":0.000028337605,"MEAN_MOTION_DOT":9.9e-7,"MEAN_MOTION_DDOT":0},{"OBJECT_NAME":"IRIDIUM 146","OBJECT_ID":"2018-030F","EPOCH":"2026-07-17T05:50:59.460000","CLASSIFICATION_TYPE":"U","MEAN_MOTION":14.34217605,"ECCENTRICITY":0.00023802,"INCLINATION":86.3957,"RA_OF_ASC_NODE":277.8512,"ARG_OF_PERICENTER":95.8354,"MEAN_ANOMALY":264.3113,"EPHEMERIS_TYPE":0,"NORAD_CAT_ID":43254,"ELEMENT_SET_NO":999,"REV_AT_EPOCH":43444,"BSTAR":0.000014117027,"MEAN_MOTION_DOT":5.9e-7,"MEAN_MOTION_DDOT":0},{"OBJECT_NAME":"IRIDIUM 148","OBJECT_ID":"2018-030G","EPOCH":"2026-07-17T05:05:19.627008","CLASSIFICATION_TYPE":"U","MEAN_MOTION":14.34218503,"ECCENTRICITY":0.00023401,"INCLINATION":86.3958,"RA_OF_ASC_NODE":277.9079,"ARG_OF_PERICENTER":92.9846,"MEAN_ANOMALY":267.1617,"EPHEMERIS_TYPE":0,"NORAD_CAT_ID":43255,"ELEMENT_SET_NO":999,"REV_AT_EPOCH":43447,"BSTAR":0.000042982549,"MEAN_MOTION_DOT":0.0000014,"MEAN_MOTION_DDOT":0},{"OBJECT_NAME":"IRIDIUM 142","OBJECT_ID":"2018-030H","EPOCH":"2026-07-17T04:19:39.469152","CLASSIFICATION_TYPE":"U","MEAN_MOTION":14.34217884,"ECCENTRICITY":0.00024441,"INCLINATION":86.3954,"RA_OF_ASC_NODE":277.8091,"ARG_OF_PERICENTER":96.1549,"MEAN_ANOMALY":263.9925,"EPHEMERIS_TYPE":0,"NORAD_CAT_ID":43256,"ELEMENT_SET_NO":999,"REV_AT_EPOCH":43443,"BSTAR":0.000011404919,"MEAN_MOTION_DOT":5.2e-7,"MEAN_MOTION_DDOT":0},{"OBJECT_NAME":"IRIDIUM 150","OBJECT_ID":"2018-030J","EPOCH":"2026-07-17T05:14:27.356352","CLASSIFICATION_TYPE":"U","MEAN_MOTION":14.34217456,"ECCENTRICITY":0.00022899,"INCLINATION":86.3958,"RA_OF_ASC_NODE":277.9106,"ARG_OF_PERICENTER":96.413,"MEAN_ANOMALY":263.7327,"EPHEMERIS_TYPE":0,"NORAD_CAT_ID":43257,"ELEMENT_SET_NO":999,"REV_AT_EPOCH":43446,"BSTAR":0.000046880877,"MEAN_MOTION_DOT":0.00000151,"MEAN_MOTION_DDOT":0},{"OBJECT_NAME":"IRIDIUM 143","OBJECT_ID":"2018-030K","EPOCH":"2026-07-16T18:44:15.525600","CLASSIFICATION_TYPE":"U","MEAN_MOTION":14.34217816,"ECCENTRICITY":0.00023437,"INCLINATION":86.3961,"RA_OF_ASC_NODE":278.1873,"ARG_OF_PERICENTER":96.7905,"MEAN_ANOMALY":263.3557,"EPHEMERIS_TYPE":0,"NORAD_CAT_ID":43258,"ELEMENT_SET_NO":999,"REV_AT_EPOCH":43433,"BSTAR":0.000024699509,"MEAN_MOTION_DOT":8.9e-7,"MEAN_MOTION_DDOT":0},{"OBJECT_NAME":"IRIDIUM 161","OBJECT_ID":"2018-047C","EPOCH":"2026-07-17T04:32:30.871680","CLASSIFICATION_TYPE":"U","MEAN_MOTION":14.43276266,"ECCENTRICITY":0.00022265,"INCLINATION":86.446,"RA_OF_ASC_NODE":75.924,"ARG_OF_PERICENTER":80.7125,"MEAN_ANOMALY":279.4328,"EPHEMERIS_TYPE":0,"NORAD_CAT_ID":43478,"ELEMENT_SET_NO":999,"REV_AT_EPOCH":42946,"BSTAR":0.000038757401,"MEAN_MOTION_DOT":0.00000151,"MEAN_MOTION_DDOT":0},{"OBJECT_NAME":"IRIDIUM 152","OBJECT_ID":"2018-047D","EPOCH":"2026-07-17T04:07:46.267392","CLASSIFICATION_TYPE":"U","MEAN_MOTION":14.34218441,"ECCENTRICITY":0.00021368,"INCLINATION":86.3933,"RA_OF_ASC_NODE":75.7924,"ARG_OF_PERICENTER":84.1747,"MEAN_ANOMALY":275.9693,"EPHEMERIS_TYPE":0,"NORAD_CAT_ID":43479,"ELEMENT_SET_NO":999,"REV_AT_EPOCH":42678,"BSTAR":0.000013723552,"MEAN_MOTION_DOT":5.8e-7,"MEAN_MOTION_DDOT":0},{"OBJECT_NAME":"IRIDIUM 147","OBJECT_ID":"2018-047E","EPOCH":"2026-07-17T04:16:54.276672","CLASSIFICATION_TYPE":"U","MEAN_MOTION":14.34217463,"ECCENTRICITY":0.00022751,"INCLINATION":86.3936,"RA_OF_ASC_NODE":75.7955,"ARG_OF_PERICENTER":88.5088,"MEAN_ANOMALY":271.6368,"EPHEMERIS_TYPE":0,"NORAD_CAT_ID":43480,"ELEMENT_SET_NO":999,"REV_AT_EPOCH":42678,"BSTAR":0.000017947654,"MEAN_MOTION_DOT":7e-7,"MEAN_MOTION_DDOT":0},{"OBJECT_NAME":"IRIDIUM 110","OBJECT_ID":"2018-047F","EPOCH":"2026-07-16T23:24:38.062656","CLASSIFICATION_TYPE":"U","MEAN_MOTION":14.34219041,"ECCENTRICITY":0.00020782,"INCLINATION":86.3939,"RA_OF_ASC_NODE":75.9732,"ARG_OF_PERICENTER":77.6883,"MEAN_ANOMALY":282.4545,"EPHEMERIS_TYPE":0,"NORAD_CAT_ID":43481,"ELEMENT_SET_NO":999,"REV_AT_EPOCH":42674,"BSTAR":0.000044308351,"MEAN_MOTION_DOT":0.00000144,"MEAN_MOTION_DDOT":0},{"OBJECT_NAME":"IRIDIUM 162","OBJECT_ID":"2018-047G","EPOCH":"2026-07-17T02:43:36.482880","CLASSIFICATION_TYPE":"U","MEAN_MOTION":14.43279058,"ECCENTRICITY":0.00021949,"INCLINATION":86.4458,"RA_OF_ASC_NODE":75.8462,"ARG_OF_PERICENTER":87.176,"MEAN_ANOMALY":272.9692,"EPHEMERIS_TYPE":0,"NORAD_CAT_ID":43482,"ELEMENT_SET_NO":999,"REV_AT_EPOCH":42944,"BSTAR":0.000045903646,"MEAN_MOTION_DOT":0.00000175,"MEAN_MOTION_DDOT":0},{"OBJECT_NAME":"IRIDIUM 160","OBJECT_ID":"2018-061A","EPOCH":"2026-07-17T06:28:58.435392","CLASSIFICATION_TYPE":"U","MEAN_MOTION":14.34217554,"ECCENTRICITY":0.00022252,"INCLINATION":86.3939,"RA_OF_ASC_NODE":44.2136,"ARG_OF_PERICENTER":86.7783,"MEAN_ANOMALY":273.3667,"EPHEMERIS_TYPE":0,"NORAD_CAT_ID":43569,"ELEMENT_SET_NO":999,"REV_AT_EPOCH":41768,"BSTAR":0.000036632526,"MEAN_MOTION_DOT":0.00000122,"MEAN_MOTION_DDOT":0},{"OBJECT_NAME":"IRIDIUM 166","OBJECT_ID":"2018-061B","EPOCH":"2026-07-16T22:43:10.493472","CLASSIFICATION_TYPE":"U","MEAN_MOTION":14.34217765,"ECCENTRICITY":0.00022838,"INCLINATION":86.3938,"RA_OF_ASC_NODE":44.2991,"ARG_OF_PERICENTER":89.8455,"MEAN_ANOMALY":270.3003,"EPHEMERIS_TYPE":0,"NORAD_CAT_ID":43570,"ELEMENT_SET_NO":999,"REV_AT_EPOCH":41766,"BSTAR":0.000008334727,"MEAN_MOTION_DOT":4.3e-7,"MEAN_MOTION_DDOT":0},{"OBJECT_NAME":"IRIDIUM 158","OBJECT_ID":"2018-061C","EPOCH":"2026-07-16T23:37:58.438560","CLASSIFICATION_TYPE":"U","MEAN_MOTION":14.34217889,"ECCENTRICITY":0.00021028,"INCLINATION":86.3938,"RA_OF_ASC_NODE":44.2926,"ARG_OF_PERICENTER":88.2698,"MEAN_ANOMALY":271.8739,"EPHEMERIS_TYPE":0,"NORAD_CAT_ID":43571,"ELEMENT_SET_NO":999,"REV_AT_EPOCH":41763,"BSTAR":0.00001350543,"MEAN_MOTION_DOT":5.8e-7,"MEAN_MOTION_DDOT":0},{"OBJECT_NAME":"IRIDIUM 165","OBJECT_ID":"2018-061D","EPOCH":"2026-07-17T00:14:30.575040","CLASSIFICATION_TYPE":"U","MEAN_MOTION":14.34217293,"ECCENTRICITY":0.00022777,"INCLINATION":86.3939,"RA_OF_ASC_NODE":44.3292,"ARG_OF_PERICENTER":90.1879,"MEAN_ANOMALY":269.9578,"EPHEMERIS_TYPE":0,"NORAD_CAT_ID":43572,"ELEMENT_SET_NO":999,"REV_AT_EPOCH":41766,"BSTAR":0.000006931594,"MEAN_MOTION_DOT":3.9e-7,"MEAN_MOTION_DDOT":0},{"OBJECT_NAME":"IRIDIUM 155","OBJECT_ID":"2018-061E","EPOCH":"2026-07-16T23:19:42.479616","CLASSIFICATION_TYPE":"U","MEAN_MOTION":14.3421757,"ECCENTRICITY":0.00021396,"INCLINATION":86.3937,"RA_OF_ASC_NODE":44.2133,"ARG_OF_PERICENTER":89.66,"MEAN_ANOMALY":270.4841,"EPHEMERIS_TYPE":0,"NORAD_CAT_ID":43573,"ELEMENT_SET_NO":999,"REV_AT_EPOCH":41762,"BSTAR":0.000009237055,"MEAN_MOTION_DOT":4.6e-7,"MEAN_MOTION_DDOT":0},{"OBJECT_NAME":"IRIDIUM 154","OBJECT_ID":"2018-061F","EPOCH":"2026-07-17T00:32:46.461408","CLASSIFICATION_TYPE":"U","MEAN_MOTION":14.34217536,"ECCENTRICITY":0.00023019,"INCLINATION":86.394,"RA_OF_ASC_NODE":44.3267,"ARG_OF_PERICENTER":90.0435,"MEAN_ANOMALY":270.1025,"EPHEMERIS_TYPE":0,"NORAD_CAT_ID":43574,"ELEMENT_SET_NO":999,"REV_AT_EPOCH":41768,"BSTAR":0.000006763842,"MEAN_MOTION_DOT":3.9e-7,"MEAN_MOTION_DDOT":0},{"OBJECT_NAME":"IRIDIUM 163","OBJECT_ID":"2018-061G","EPOCH":"2026-07-17T06:47:14.529120","CLASSIFICATION_TYPE":"U","MEAN_MOTION":14.34217115,"ECCENTRICITY":0.00020066,"INCLINATION":86.3934,"RA_OF_ASC_NODE":44.1321,"ARG_OF_PERICENTER":85.3111,"MEAN_ANOMALY":274.8314,"EPHEMERIS_TYPE":0,"NORAD_CAT_ID":43575,"ELEMENT_SET_NO":999,"REV_AT_EPOCH":41769,"BSTAR":-0.000002228188,"MEAN_MOTION_DOT":1.4e-7,"MEAN_MOTION_DDOT":0},{"OBJECT_NAME":"IRIDIUM 156","OBJECT_ID":"2018-061H","EPOCH":"2026-07-17T01:09:18.423360","CLASSIFICATION_TYPE":"U","MEAN_MOTION":14.34218044,"ECCENTRICITY":0.00021268,"INCLINATION":86.3936,"RA_OF_ASC_NODE":44.2377,"ARG_OF_PERICENTER":93.4368,"MEAN_ANOMALY":266.7071,"EPHEMERIS_TYPE":0,"NORAD_CAT_ID":43576,"ELEMENT_SET_NO":999,"REV_AT_EPOCH":41765,"BSTAR":0.000016627487,"MEAN_MOTION_DOT":6.6e-7,"MEAN_MOTION_DDOT":0},{"OBJECT_NAME":"IRIDIUM 164","OBJECT_ID":"2018-061J","EPOCH":"2026-07-17T00:41:54.505248","CLASSIFICATION_TYPE":"U","MEAN_MOTION":14.34218566,"ECCENTRICITY":0.00023392,"INCLINATION":86.3938,"RA_OF_ASC_NODE":44.2866,"ARG_OF_PERICENTER":89.1929,"MEAN_ANOMALY":270.9535,"EPHEMERIS_TYPE":0,"NORAD_CAT_ID":43577,"ELEMENT_SET_NO":999,"REV_AT_EPOCH":41769,"BSTAR":0.00003352673,"MEAN_MOTION_DOT":0.00000114,"MEAN_MOTION_DDOT":0},{"OBJECT_NAME":"IRIDIUM 159","OBJECT_ID":"2018-061K","EPOCH":"2026-07-17T06:38:06.456768","CLASSIFICATION_TYPE":"U","MEAN_MOTION":14.34217636,"ECCENTRICITY":0.00021341,"INCLINATION":86.3935,"RA_OF_ASC_NODE":44.1194,"ARG_OF_PERICENTER":85.8386,"MEAN_ANOMALY":274.3053,"EPHEMERIS_TYPE":0,"NORAD_CAT_ID":43578,"ELEMENT_SET_NO":999,"REV_AT_EPOCH":41769,"BSTAR":0.000009113229,"MEAN_MOTION_DOT":4.5e-7,"MEAN_MOTION_DDOT":0},{"OBJECT_NAME":"IRIDIUM 180","OBJECT_ID":"2019-002A","EPOCH":"2026-07-16T22:15:02.952864","CLASSIFICATION_TYPE":"U","MEAN_MOTION":14.34217889,"ECCENTRICITY":0.00021658,"INCLINATION":86.3993,"RA_OF_ASC_NODE":341.1653,"ARG_OF_PERICENTER":91.885,"MEAN_ANOMALY":268.2594,"EPHEMERIS_TYPE":0,"NORAD_CAT_ID":43922,"ELEMENT_SET_NO":999,"REV_AT_EPOCH":39325,"BSTAR":0.000032166327,"MEAN_MOTION_DOT":0.0000011,"MEAN_MOTION_DDOT":0},{"OBJECT_NAME":"IRIDIUM 176","OBJECT_ID":"2019-002B","EPOCH":"2026-07-17T08:04:56.573760","CLASSIFICATION_TYPE":"U","MEAN_MOTION":14.72250602,"ECCENTRICITY":0.00023331,"INCLINATION":86.6114,"RA_OF_ASC_NODE":340.9333,"ARG_OF_PERICENTER":90.3542,"MEAN_ANOMALY":269.7943,"EPHEMERIS_TYPE":0,"NORAD_CAT_ID":43923,"ELEMENT_SET_NO":999,"REV_AT_EPOCH":40368,"BSTAR":0.000055954817,"MEAN_MOTION_DOT":0.00000377,"MEAN_MOTION_DDOT":0},{"OBJECT_NAME":"IRIDIUM 168","OBJECT_ID":"2019-002C","EPOCH":"2026-07-17T08:08:43.043712","CLASSIFICATION_TYPE":"U","MEAN_MOTION":14.34216837,"ECCENTRICITY":0.00021859,"INCLINATION":86.3996,"RA_OF_ASC_NODE":341.0709,"ARG_OF_PERICENTER":90.4019,"MEAN_ANOMALY":269.7427,"EPHEMERIS_TYPE":0,"NORAD_CAT_ID":43924,"ELEMENT_SET_NO":999,"REV_AT_EPOCH":39329,"BSTAR":-0.000001181993,"MEAN_MOTION_DOT":1.6e-7,"MEAN_MOTION_DDOT":0},{"OBJECT_NAME":"IRIDIUM 173","OBJECT_ID":"2019-002D","EPOCH":"2026-07-16T21:47:38.969088","CLASSIFICATION_TYPE":"U","MEAN_MOTION":14.34217637,"ECCENTRICITY":0.00020312,"INCLINATION":86.3987,"RA_OF_ASC_NODE":341.1392,"ARG_OF_PERICENTER":92.7726,"MEAN_ANOMALY":267.3703,"EPHEMERIS_TYPE":0,"NORAD_CAT_ID":43925,"ELEMENT_SET_NO":999,"REV_AT_EPOCH":39321,"BSTAR":-0.000032132772,"MEAN_MOTION_DOT":-7e-7,"MEAN_MOTION_DDOT":0},{"OBJECT_NAME":"IRIDIUM 169","OBJECT_ID":"2019-002E","EPOCH":"2026-07-17T05:32:15.152352","CLASSIFICATION_TYPE":"U","MEAN_MOTION":14.38613573,"ECCENTRICITY":0.00019623,"INCLINATION":86.4223,"RA_OF_ASC_NODE":12.6286,"ARG_OF_PERICENTER":104.378,"MEAN_ANOMALY":255.7636,"EPHEMERIS_TYPE":0,"NORAD_CAT_ID":43926,"ELEMENT_SET_NO":999,"REV_AT_EPOCH":39454,"BSTAR":0.000013169384,"MEAN_MOTION_DOT":6e-7,"MEAN_MOTION_DDOT":0},{"OBJECT_NAME":"IRIDIUM 172","OBJECT_ID":"2019-002F","EPOCH":"2026-07-16T23:18:59.018688","CLASSIFICATION_TYPE":"U","MEAN_MOTION":14.34217631,"ECCENTRICITY":0.00021859,"INCLINATION":86.3992,"RA_OF_ASC_NODE":341.1202,"ARG_OF_PERICENTER":91.3558,"MEAN_ANOMALY":268.7888,"EPHEMERIS_TYPE":0,"NORAD_CAT_ID":43927,"ELEMENT_SET_NO":999,"REV_AT_EPOCH":39323,"BSTAR":0.00000490773,"MEAN_MOTION_DOT":3.4e-7,"MEAN_MOTION_DDOT":0},{"OBJECT_NAME":"IRIDIUM 175","OBJECT_ID":"2019-002G","EPOCH":"2026-07-17T05:16:22.913760","CLASSIFICATION_TYPE":"U","MEAN_MOTION":14.43627862,"ECCENTRICITY":0.00054076,"INCLINATION":86.4511,"RA_OF_ASC_NODE":277.968,"ARG_OF_PERICENTER":111.5164,"MEAN_ANOMALY":248.6614,"EPHEMERIS_TYPE":0,"NORAD_CAT_ID":43928,"ELEMENT_SET_NO":999,"REV_AT_EPOCH":40331,"BSTAR":0.000044293262,"MEAN_MOTION_DOT":0.0000017,"MEAN_MOTION_DDOT":0},{"OBJECT_NAME":"IRIDIUM 171","OBJECT_ID":"2019-002H","EPOCH":"2026-07-16T22:51:34.962336","CLASSIFICATION_TYPE":"U","MEAN_MOTION":14.34217839,"ECCENTRICITY":0.00022447,"INCLINATION":86.4002,"RA_OF_ASC_NODE":341.4376,"ARG_OF_PERICENTER":94.8167,"MEAN_ANOMALY":265.3286,"EPHEMERIS_TYPE":0,"NORAD_CAT_ID":43929,"ELEMENT_SET_NO":999,"REV_AT_EPOCH":39322,"BSTAR":0.00001161357,"MEAN_MOTION_DOT":5.2e-7,"MEAN_MOTION_DDOT":0},{"OBJECT_NAME":"IRIDIUM 170","OBJECT_ID":"2019-002J","EPOCH":"2026-07-16T22:26:35.074752","CLASSIFICATION_TYPE":"U","MEAN_MOTION":14.72250887,"ECCENTRICITY":0.00022381,"INCLINATION":86.6112,"RA_OF_ASC_NODE":341.1033,"ARG_OF_PERICENTER":87.1001,"MEAN_ANOMALY":273.0472,"EPHEMERIS_TYPE":0,"NORAD_CAT_ID":43930,"ELEMENT_SET_NO":999,"REV_AT_EPOCH":40363,"BSTAR":0.000055229428,"MEAN_MOTION_DOT":0.00000373,"MEAN_MOTION_DDOT":0},{"OBJECT_NAME":"IRIDIUM 167","OBJECT_ID":"2019-002K","EPOCH":"2026-07-16T22:42:26.958240","CLASSIFICATION_TYPE":"U","MEAN_MOTION":14.3421774,"ECCENTRICITY":0.00023241,"INCLINATION":86.3994,"RA_OF_ASC_NODE":341.1537,"ARG_OF_PERICENTER":98.3232,"MEAN_ANOMALY":261.8227,"EPHEMERIS_TYPE":0,"NORAD_CAT_ID":43931,"ELEMENT_SET_NO":999,"REV_AT_EPOCH":39322,"BSTAR":0.000004515042,"MEAN_MOTION_DOT":3.2e-7,"MEAN_MOTION_DDOT":0},{"OBJECT_NAME":"IRIDIUM 181","OBJECT_ID":"2023-068S","EPOCH":"2026-07-16T23:41:53.157984","CLASSIFICATION_TYPE":"U","MEAN_MOTION":14.43307697,"ECCENTRICITY":0.00024032,"INCLINATION":86.4475,"RA_OF_ASC_NODE":44.328,"ARG_OF_PERICENTER":84.5328,"MEAN_ANOMALY":275.6147,"EPHEMERIS_TYPE":0,"NORAD_CAT_ID":56726,"ELEMENT_SET_NO":999,"REV_AT_EPOCH":16673,"BSTAR":0.000020648068,"MEAN_MOTION_DOT":9e-7,"MEAN_MOTION_DDOT":0},{"OBJECT_NAME":"IRIDIUM 177","OBJECT_ID":"2023-068T","EPOCH":"2026-07-17T08:10:25.470048","CLASSIFICATION_TYPE":"U","MEAN_MOTION":14.80025922,"ECCENTRICITY":0.00021975,"INCLINATION":86.1987,"RA_OF_ASC_NODE":314.476,"ARG_OF_PERICENTER":96.6258,"MEAN_ANOMALY":263.5213,"EPHEMERIS_TYPE":0,"NORAD_CAT_ID":56727,"ELEMENT_SET_NO":999,"REV_AT_EPOCH":17082,"BSTAR":0.000068021474,"MEAN_MOTION_DOT":0.00000541,"MEAN_MOTION_DDOT":0},{"OBJECT_NAME":"IRIDIUM 174","OBJECT_ID":"2023-068U","EPOCH":"2026-07-17T07:55:53.413248","CLASSIFICATION_TYPE":"U","MEAN_MOTION":14.72259778,"ECCENTRICITY":0.00019833,"INCLINATION":86.6121,"RA_OF_ASC_NODE":341.0885,"ARG_OF_PERICENTER":89.3733,"MEAN_ANOMALY":270.7712,"EPHEMERIS_TYPE":0,"NORAD_CAT_ID":56728,"ELEMENT_SET_NO":999,"REV_AT_EPOCH":17045,"BSTAR":0.000056672231,"MEAN_MOTION_DOT":0.00000382,"MEAN_MOTION_DDOT":0},{"OBJECT_NAME":"IRIDIUM 178","OBJECT_ID":"2023-068V","EPOCH":"2026-07-16T22:10:25.504320","CLASSIFICATION_TYPE":"U","MEAN_MOTION":14.80028189,"ECCENTRICITY":0.00022815,"INCLINATION":86.6537,"RA_OF_ASC_NODE":12.9311,"ARG_OF_PERICENTER":90.817,"MEAN_ANOMALY":269.3312,"EPHEMERIS_TYPE":0,"NORAD_CAT_ID":56729,"ELEMENT_SET_NO":999,"REV_AT_EPOCH":17076,"BSTAR":0.000019584044,"MEAN_MOTION_DOT":0.00000174,"MEAN_MOTION_DDOT":0},{"OBJECT_NAME":"IRIDIUM 179","OBJECT_ID":"2023-068W","EPOCH":"2026-07-16T23:40:04.946304","CLASSIFICATION_TYPE":"U","MEAN_MOTION":14.80023217,"ECCENTRICITY":0.00023516,"INCLINATION":86.6768,"RA_OF_ASC_NODE":21.9724,"ARG_OF_PERICENTER":93.5958,"MEAN_ANOMALY":266.5533,"EPHEMERIS_TYPE":0,"NORAD_CAT_ID":56730,"ELEMENT_SET_NO":999,"REV_AT_EPOCH":17077,"BSTAR":0.000008250573,"MEAN_MOTION_DOT":8.9e-7,"MEAN_MOTION_DDOT":0}]}
