{"fetched_at":"2026-07-07T18:29:35.104Z","source":"https://celestrak.org/NORAD/elements/gp.php?NAME=KINEIS&FORMAT=JSON","constellation":"kineis","records":[{"OBJECT_NAME":"KINEIS-1B","OBJECT_ID":"2024-114A","EPOCH":"2026-07-07T11:03:48.602016","CLASSIFICATION_TYPE":"U","MEAN_MOTION":14.80658752,"ECCENTRICITY":0.0003454,"INCLINATION":97.9826,"RA_OF_ASC_NODE":212.5496,"ARG_OF_PERICENTER":55.1098,"MEAN_ANOMALY":305.0438,"EPHEMERIS_TYPE":0,"NORAD_CAT_ID":60079,"ELEMENT_SET_NO":999,"REV_AT_EPOCH":11040,"BSTAR":0.000095679,"MEAN_MOTION_DOT":0.00000682,"MEAN_MOTION_DDOT":0},{"OBJECT_NAME":"KINEIS-1C","OBJECT_ID":"2024-114C","EPOCH":"2026-07-07T11:52:15.225888","CLASSIFICATION_TYPE":"U","MEAN_MOTION":14.80660926,"ECCENTRICITY":0.00025,"INCLINATION":97.9841,"RA_OF_ASC_NODE":212.4366,"ARG_OF_PERICENTER":104.487,"MEAN_ANOMALY":255.6619,"EPHEMERIS_TYPE":0,"NORAD_CAT_ID":60081,"ELEMENT_SET_NO":999,"REV_AT_EPOCH":11038,"BSTAR":0.000090137,"MEAN_MOTION_DOT":0.0000064,"MEAN_MOTION_DDOT":0},{"OBJECT_NAME":"KINEIS-1D","OBJECT_ID":"2024-114D","EPOCH":"2026-07-07T12:17:51.558720","CLASSIFICATION_TYPE":"U","MEAN_MOTION":14.76355782,"ECCENTRICITY":0.0002828,"INCLINATION":97.9882,"RA_OF_ASC_NODE":208.4256,"ARG_OF_PERICENTER":110.0214,"MEAN_ANOMALY":250.13,"EPHEMERIS_TYPE":0,"NORAD_CAT_ID":60082,"ELEMENT_SET_NO":999,"REV_AT_EPOCH":11012,"BSTAR":0.000079894,"MEAN_MOTION_DOT":0.00000504,"MEAN_MOTION_DDOT":0},{"OBJECT_NAME":"KINEIS-1E","OBJECT_ID":"2024-114E","EPOCH":"2026-07-07T12:18:05.154624","CLASSIFICATION_TYPE":"U","MEAN_MOTION":14.80684632,"ECCENTRICITY":0.0003836,"INCLINATION":97.8943,"RA_OF_ASC_NODE":211.6089,"ARG_OF_PERICENTER":125.4761,"MEAN_ANOMALY":234.6809,"EPHEMERIS_TYPE":0,"NORAD_CAT_ID":60083,"ELEMENT_SET_NO":999,"REV_AT_EPOCH":11039,"BSTAR":0.00012316,"MEAN_MOTION_DOT":0.00000895,"MEAN_MOTION_DDOT":0},{"OBJECT_NAME":"KINEIS-1A","OBJECT_ID":"2024-114F","EPOCH":"2026-07-07T11:28:50.832768","CLASSIFICATION_TYPE":"U","MEAN_MOTION":14.80673874,"ECCENTRICITY":0.0005652,"INCLINATION":97.8916,"RA_OF_ASC_NODE":211.6717,"ARG_OF_PERICENTER":80.8267,"MEAN_ANOMALY":279.3585,"EPHEMERIS_TYPE":0,"NORAD_CAT_ID":60084,"ELEMENT_SET_NO":999,"REV_AT_EPOCH":11039,"BSTAR":0.000098621,"MEAN_MOTION_DOT":0.00000706,"MEAN_MOTION_DDOT":0},{"OBJECT_NAME":"KINEIS-3C","OBJECT_ID":"2024-172A","EPOCH":"2026-07-07T04:32:23.399808","CLASSIFICATION_TYPE":"U","MEAN_MOTION":14.72354106,"ECCENTRICITY":0.0002812,"INCLINATION":98.043,"RA_OF_ASC_NODE":277.8766,"ARG_OF_PERICENTER":94.8849,"MEAN_ANOMALY":265.2679,"EPHEMERIS_TYPE":0,"NORAD_CAT_ID":61220,"ELEMENT_SET_NO":999,"REV_AT_EPOCH":9601,"BSTAR":0.00025036,"MEAN_MOTION_DOT":0.00001535,"MEAN_MOTION_DDOT":0},{"OBJECT_NAME":"KINEIS-3D","OBJECT_ID":"2024-172B","EPOCH":"2026-07-07T02:44:49.603200","CLASSIFICATION_TYPE":"U","MEAN_MOTION":14.72355741,"ECCENTRICITY":0.0002624,"INCLINATION":98.0427,"RA_OF_ASC_NODE":277.8129,"ARG_OF_PERICENTER":94.4977,"MEAN_ANOMALY":265.653,"EPHEMERIS_TYPE":0,"NORAD_CAT_ID":61221,"ELEMENT_SET_NO":999,"REV_AT_EPOCH":9628,"BSTAR":0.00025341,"MEAN_MOTION_DOT":0.00001554,"MEAN_MOTION_DDOT":0},{"OBJECT_NAME":"KINEIS-3E","OBJECT_ID":"2024-172C","EPOCH":"2026-07-07T12:07:29.965152","CLASSIFICATION_TYPE":"U","MEAN_MOTION":14.72323692,"ECCENTRICITY":0.0001884,"INCLINATION":98.0423,"RA_OF_ASC_NODE":278.1812,"ARG_OF_PERICENTER":94.899,"MEAN_ANOMALY":265.2432,"EPHEMERIS_TYPE":0,"NORAD_CAT_ID":61222,"ELEMENT_SET_NO":999,"REV_AT_EPOCH":9634,"BSTAR":0.00022663,"MEAN_MOTION_DOT":0.00001383,"MEAN_MOTION_DDOT":0},{"OBJECT_NAME":"KINEIS-3A","OBJECT_ID":"2024-172D","EPOCH":"2026-07-07T11:43:37.536096","CLASSIFICATION_TYPE":"U","MEAN_MOTION":14.72293519,"ECCENTRICITY":0.0002681,"INCLINATION":98.0419,"RA_OF_ASC_NODE":278.2632,"ARG_OF_PERICENTER":58.132,"MEAN_ANOMALY":302.0148,"EPHEMERIS_TYPE":0,"NORAD_CAT_ID":61223,"ELEMENT_SET_NO":999,"REV_AT_EPOCH":9576,"BSTAR":0.00023272,"MEAN_MOTION_DOT":0.00001421,"MEAN_MOTION_DDOT":0},{"OBJECT_NAME":"KINEIS-3B","OBJECT_ID":"2024-172E","EPOCH":"2026-07-07T04:47:02.253696","CLASSIFICATION_TYPE":"U","MEAN_MOTION":14.72278926,"ECCENTRICITY":0.0002209,"INCLINATION":98.0412,"RA_OF_ASC_NODE":278.0002,"ARG_OF_PERICENTER":46.7741,"MEAN_ANOMALY":313.365,"EPHEMERIS_TYPE":0,"NORAD_CAT_ID":61224,"ELEMENT_SET_NO":999,"REV_AT_EPOCH":9629,"BSTAR":0.00023614,"MEAN_MOTION_DOT":0.00001442,"MEAN_MOTION_DDOT":0},{"OBJECT_NAME":"KINEIS-5C","OBJECT_ID":"2024-219A","EPOCH":"2026-07-07T12:23:41.337888","CLASSIFICATION_TYPE":"U","MEAN_MOTION":14.72307797,"ECCENTRICITY":0.0003511,"INCLINATION":97.906,"RA_OF_ASC_NODE":346.8059,"ARG_OF_PERICENTER":197.6792,"MEAN_ANOMALY":162.4294,"EPHEMERIS_TYPE":0,"NORAD_CAT_ID":62081,"ELEMENT_SET_NO":999,"REV_AT_EPOCH":8674,"BSTAR":0.000092105,"MEAN_MOTION_DOT":0.00000534,"MEAN_MOTION_DDOT":0},{"OBJECT_NAME":"KINEIS-5D","OBJECT_ID":"2024-219B","EPOCH":"2026-07-07T11:25:20.956800","CLASSIFICATION_TYPE":"U","MEAN_MOTION":14.7248387,"ECCENTRICITY":0.0004636,"INCLINATION":97.9171,"RA_OF_ASC_NODE":346.8217,"ARG_OF_PERICENTER":191.3784,"MEAN_ANOMALY":168.732,"EPHEMERIS_TYPE":0,"NORAD_CAT_ID":62082,"ELEMENT_SET_NO":999,"REV_AT_EPOCH":8674,"BSTAR":0.0001313,"MEAN_MOTION_DOT":0.00000785,"MEAN_MOTION_DDOT":0},{"OBJECT_NAME":"KINEIS-5E","OBJECT_ID":"2024-219C","EPOCH":"2026-07-07T11:49:33.525696","CLASSIFICATION_TYPE":"U","MEAN_MOTION":14.72292775,"ECCENTRICITY":0.0006135,"INCLINATION":97.9016,"RA_OF_ASC_NODE":346.8814,"ARG_OF_PERICENTER":188.3558,"MEAN_ANOMALY":171.7549,"EPHEMERIS_TYPE":0,"NORAD_CAT_ID":62083,"ELEMENT_SET_NO":999,"REV_AT_EPOCH":8675,"BSTAR":0.000088385,"MEAN_MOTION_DOT":0.0000051,"MEAN_MOTION_DDOT":0},{"OBJECT_NAME":"KINEIS-5A","OBJECT_ID":"2024-219D","EPOCH":"2026-07-06T10:49:46.443072","CLASSIFICATION_TYPE":"U","MEAN_MOTION":14.72289083,"ECCENTRICITY":0.00031406,"INCLINATION":97.8957,"RA_OF_ASC_NODE":346.1558,"ARG_OF_PERICENTER":233.6875,"MEAN_ANOMALY":126.4043,"EPHEMERIS_TYPE":0,"NORAD_CAT_ID":62084,"ELEMENT_SET_NO":999,"REV_AT_EPOCH":8660,"BSTAR":0.00019838985,"MEAN_MOTION_DOT":0.00001205,"MEAN_MOTION_DDOT":0},{"OBJECT_NAME":"KINEIS-5B","OBJECT_ID":"2024-219E","EPOCH":"2026-07-07T11:42:56.866752","CLASSIFICATION_TYPE":"U","MEAN_MOTION":14.78374336,"ECCENTRICITY":0.0001937,"INCLINATION":98.0082,"RA_OF_ASC_NODE":352.2066,"ARG_OF_PERICENTER":161.183,"MEAN_ANOMALY":198.9452,"EPHEMERIS_TYPE":0,"NORAD_CAT_ID":62085,"ELEMENT_SET_NO":999,"REV_AT_EPOCH":8700,"BSTAR":0.00013108,"MEAN_MOTION_DOT":0.00000902,"MEAN_MOTION_DDOT":0},{"OBJECT_NAME":"KINEIS-2C","OBJECT_ID":"2025-028B","EPOCH":"2026-07-07T03:37:27.682176","CLASSIFICATION_TYPE":"U","MEAN_MOTION":14.73413024,"ECCENTRICITY":0.0003576,"INCLINATION":98.1233,"RA_OF_ASC_NODE":242.566,"ARG_OF_PERICENTER":181.8671,"MEAN_ANOMALY":178.2524,"EPHEMERIS_TYPE":0,"NORAD_CAT_ID":62929,"ELEMENT_SET_NO":999,"REV_AT_EPOCH":7555,"BSTAR":0.00022406,"MEAN_MOTION_DOT":0.00001402,"MEAN_MOTION_DDOT":0},{"OBJECT_NAME":"KINEIS-2D","OBJECT_ID":"2025-028C","EPOCH":"2026-07-07T09:26:54.184416","CLASSIFICATION_TYPE":"U","MEAN_MOTION":14.75752487,"ECCENTRICITY":0.0004491,"INCLINATION":97.9276,"RA_OF_ASC_NODE":240.45,"ARG_OF_PERICENTER":126.4396,"MEAN_ANOMALY":233.7228,"EPHEMERIS_TYPE":0,"NORAD_CAT_ID":62930,"ELEMENT_SET_NO":999,"REV_AT_EPOCH":7569,"BSTAR":0.0002239,"MEAN_MOTION_DOT":0.00001483,"MEAN_MOTION_DDOT":0},{"OBJECT_NAME":"KINEIS-2E","OBJECT_ID":"2025-028D","EPOCH":"2026-07-07T03:24:08.553024","CLASSIFICATION_TYPE":"U","MEAN_MOTION":14.77072473,"ECCENTRICITY":0.0002127,"INCLINATION":97.8944,"RA_OF_ASC_NODE":239.3498,"ARG_OF_PERICENTER":101.1848,"MEAN_ANOMALY":258.9602,"EPHEMERIS_TYPE":0,"NORAD_CAT_ID":62931,"ELEMENT_SET_NO":999,"REV_AT_EPOCH":7572,"BSTAR":0.00019502,"MEAN_MOTION_DOT":0.00001327,"MEAN_MOTION_DDOT":0},{"OBJECT_NAME":"KINEIS-2A","OBJECT_ID":"2025-028E","EPOCH":"2026-07-07T09:36:25.496640","CLASSIFICATION_TYPE":"U","MEAN_MOTION":14.73437108,"ECCENTRICITY":0.0006055,"INCLINATION":98.1291,"RA_OF_ASC_NODE":243.816,"ARG_OF_PERICENTER":102.4333,"MEAN_ANOMALY":257.7553,"EPHEMERIS_TYPE":0,"NORAD_CAT_ID":62932,"ELEMENT_SET_NO":999,"REV_AT_EPOCH":7558,"BSTAR":0.00019505,"MEAN_MOTION_DOT":0.00001214,"MEAN_MOTION_DDOT":0},{"OBJECT_NAME":"KINEIS-2B","OBJECT_ID":"2025-028G","EPOCH":"2026-07-07T09:03:49.373856","CLASSIFICATION_TYPE":"U","MEAN_MOTION":14.7343814,"ECCENTRICITY":0.0005032,"INCLINATION":97.9658,"RA_OF_ASC_NODE":240.8727,"ARG_OF_PERICENTER":91.2682,"MEAN_ANOMALY":268.9103,"EPHEMERIS_TYPE":0,"NORAD_CAT_ID":62934,"ELEMENT_SET_NO":999,"REV_AT_EPOCH":7563,"BSTAR":0.00018868,"MEAN_MOTION_DOT":0.00001175,"MEAN_MOTION_DDOT":0},{"OBJECT_NAME":"KINEIS-4E","OBJECT_ID":"2025-056A","EPOCH":"2026-07-07T13:40:33.513312","CLASSIFICATION_TYPE":"U","MEAN_MOTION":14.72287824,"ECCENTRICITY":0.0003063,"INCLINATION":97.9061,"RA_OF_ASC_NODE":311.9016,"ARG_OF_PERICENTER":98.2477,"MEAN_ANOMALY":261.9078,"EPHEMERIS_TYPE":0,"NORAD_CAT_ID":63300,"ELEMENT_SET_NO":999,"REV_AT_EPOCH":7012,"BSTAR":0.00021747,"MEAN_MOTION_DOT":0.00001326,"MEAN_MOTION_DDOT":0},{"OBJECT_NAME":"KINEIS-4C","OBJECT_ID":"2025-056B","EPOCH":"2026-07-07T12:20:40.886304","CLASSIFICATION_TYPE":"U","MEAN_MOTION":14.72309209,"ECCENTRICITY":0.0002287,"INCLINATION":97.9114,"RA_OF_ASC_NODE":312.0913,"ARG_OF_PERICENTER":245.6239,"MEAN_ANOMALY":114.473,"EPHEMERIS_TYPE":0,"NORAD_CAT_ID":63301,"ELEMENT_SET_NO":999,"REV_AT_EPOCH":7012,"BSTAR":0.00022259,"MEAN_MOTION_DOT":0.00001359,"MEAN_MOTION_DDOT":0},{"OBJECT_NAME":"KINEIS-4D","OBJECT_ID":"2025-056C","EPOCH":"2026-07-07T10:48:05.698944","CLASSIFICATION_TYPE":"U","MEAN_MOTION":14.7241131,"ECCENTRICITY":0.0001075,"INCLINATION":97.9036,"RA_OF_ASC_NODE":312.0082,"ARG_OF_PERICENTER":262.804,"MEAN_ANOMALY":97.3046,"EPHEMERIS_TYPE":0,"NORAD_CAT_ID":63302,"ELEMENT_SET_NO":999,"REV_AT_EPOCH":7011,"BSTAR":0.00022337,"MEAN_MOTION_DOT":0.00001367,"MEAN_MOTION_DDOT":0},{"OBJECT_NAME":"KINEIS-4A","OBJECT_ID":"2025-056D","EPOCH":"2026-07-07T13:16:10.336224","CLASSIFICATION_TYPE":"U","MEAN_MOTION":14.72318904,"ECCENTRICITY":0.000151,"INCLINATION":97.913,"RA_OF_ASC_NODE":312.0519,"ARG_OF_PERICENTER":167.0009,"MEAN_ANOMALY":193.1238,"EPHEMERIS_TYPE":0,"NORAD_CAT_ID":63303,"ELEMENT_SET_NO":999,"REV_AT_EPOCH":7012,"BSTAR":0.00021632,"MEAN_MOTION_DOT":0.00001319,"MEAN_MOTION_DDOT":0},{"OBJECT_NAME":"KINEIS-4B","OBJECT_ID":"2025-056E","EPOCH":"2026-07-07T11:13:23.210400","CLASSIFICATION_TYPE":"U","MEAN_MOTION":14.72313152,"ECCENTRICITY":0.0004672,"INCLINATION":97.9141,"RA_OF_ASC_NODE":312.0252,"ARG_OF_PERICENTER":219.7168,"MEAN_ANOMALY":140.3698,"EPHEMERIS_TYPE":0,"NORAD_CAT_ID":63304,"ELEMENT_SET_NO":999,"REV_AT_EPOCH":7010,"BSTAR":0.00021709,"MEAN_MOTION_DOT":0.00001324,"MEAN_MOTION_DDOT":0}]}
